arxiv_miner/__init__.py
arxiv_miner/cli.py
arxiv_miner/config.py
arxiv_miner/constants.py
arxiv_miner/exception.py
arxiv_miner/latex_parser.py
arxiv_miner/logger.py
arxiv_miner/mining_engine.py
arxiv_miner/ontology_miner.py
arxiv_miner/paper.py
arxiv_miner/record.py
arxiv_miner/scraper.py
arxiv_miner/scraping_engine.py
arxiv_miner/utils.py
arxiv_miner/database/__init__.py
arxiv_miner/database/core.py
arxiv_miner/database/elasticsearch.py
arxiv_miner/semantic_parsing/__init__.py
arxiv_miner/semantic_parsing/constants.py
arxiv_miner/semantic_parsing/research_paper.py
arxiv_miner/semantic_parsing/structure.py
throughput_sim/__init__.py
throughput_sim/constants.py
throughput_sim/data_workers.py
throughput_sim/datasource.py
throughput_sim/rl_rep.py
throughput_sim/structures.py
arxiv_miner-2.0.3.dist-info/LICENSE.txt
arxiv_miner-2.0.3.dist-info/METADATA
arxiv_miner-2.0.3.dist-info/WHEEL
arxiv_miner-2.0.3.dist-info/top_level.txt
arxiv_miner-2.0.3.dist-info/RECORD
