Metadata-Version: 2.1
Name: arxiv-miner
Version: 2.0.3
Summary: ArXiv-Miner: Mine/Scrape Arxiv-Papers To Structured Datasets
Home-page: https://github.com/valayDave/arxiv-miner
Author: Valay Dave
Author-email: valaygaurang@gmail.com
License: Apache License 2.0
Platform: UNKNOWN
Classifier: Development Status :: 4 - Beta
Classifier: Intended Audience :: Developers
Classifier: License :: OSI Approved :: MIT License
Classifier: Programming Language :: Python :: 3.4
Classifier: Programming Language :: Python :: 3.5
Classifier: Programming Language :: Python :: 3.6
Classifier: Programming Language :: Python :: 3.7
Classifier: Programming Language :: Python :: 3.8
Requires-Dist: arxiv (==0.5.3)
Requires-Dist: tex2py
Requires-Dist: matplotlib
Requires-Dist: pandas
Requires-Dist: click
Requires-Dist: numpy
Requires-Dist: dateparser
Requires-Dist: expiringdict
Requires-Dist: elasticsearch
Requires-Dist: elasticsearch-dsl
Requires-Dist: luqum
